qolagg/__init__.py
qolagg/qolagg.py
qolagg-1.5.dist-info/LICENSE.txt
qolagg-1.5.dist-info/METADATA
qolagg-1.5.dist-info/WHEEL
qolagg-1.5.dist-info/top_level.txt
qolagg-1.5.dist-info/RECORD
