Metadata-Version: 2.1
Name: qolagg
Version: 1.5
Summary: This library code execute aggregate analysis for the Quality of Life Exporer variables
Home-page: https://github.com/ProvidenceAdu/qolagg
Author: Providence Adu,Ph.D.
Author-email: <padu@charlotte.edu>
Keywords: urban institute,python,Mecklenburg County,quality of life explorer,aggregate,NPA
License-File: LICENSE.txt
Requires-Dist: pandas (>=1.0.0)
